filterRomuere/__init__.py
filterRomuere/filterRomuere.py
filterRomuere-0.0.1.1.dist-info/LICENSE
filterRomuere-0.0.1.1.dist-info/METADATA
filterRomuere-0.0.1.1.dist-info/WHEEL
filterRomuere-0.0.1.1.dist-info/top_level.txt
filterRomuere-0.0.1.1.dist-info/RECORD
