Metadata-Version: 2.1
Name: filterRomuere
Version: 0.0.1.1
Summary: Pacote para aplicar filtragem por agrupamento
Home-page: https://github.com/romuere/filterRomuere
Author: Romuere Silva
Author-email: romuere@ufpi.edu.br
License: UNKNOWN
Platform: UNKNOWN
Classifier: Programming Language :: Python :: 3
Classifier: License :: OSI Approved :: MIT License
Classifier: Operating System :: OS Independent
Requires-Python: >=3.8
License-File: LICENSE
